odoo/addons/product_supplierinfo_picking/README.rst
odoo/addons/product_supplierinfo_picking/__init__.py
odoo/addons/product_supplierinfo_picking/__manifest__.py
odoo/addons/product_supplierinfo_picking/i18n/fr.po
odoo/addons/product_supplierinfo_picking/i18n/product_supplierinfo_picking.pot
odoo/addons/product_supplierinfo_picking/i18n/sl.po
odoo/addons/product_supplierinfo_picking/models/__init__.py
odoo/addons/product_supplierinfo_picking/models/stock_move.py
odoo/addons/product_supplierinfo_picking/readme/CONTRIBUTORS.rst
odoo/addons/product_supplierinfo_picking/readme/DESCRIPTION.rst
odoo/addons/product_supplierinfo_picking/readme/USAGE.rst
odoo/addons/product_supplierinfo_picking/static/description/icon.png
odoo/addons/product_supplierinfo_picking/static/description/index.html
odoo/addons/product_supplierinfo_picking/tests/__init__.py
odoo/addons/product_supplierinfo_picking/tests/test_product_supplierinfo_picking.py
odoo/addons/product_supplierinfo_picking/views/stock_picking_view.xml
odoo12_addon_product_supplierinfo_picking-12.0.1.0.0.99.dev7.dist-info/METADATA
odoo12_addon_product_supplierinfo_picking-12.0.1.0.0.99.dev7.dist-info/WHEEL
odoo12_addon_product_supplierinfo_picking-12.0.1.0.0.99.dev7.dist-info/top_level.txt
odoo12_addon_product_supplierinfo_picking-12.0.1.0.0.99.dev7.dist-info/RECORD
